{
    "question": "7. kedua tangan digerakkan bersama-sama digerakkan ke depan di atas permukaan air disebut    gaya..........\r\na. bebas\r\nb. rimau\r\nC.\r\ndada\r\nd. butterfly\r\ne.\r\npunggung\u200b",
    "attachments": [],
    "answers": [
        {
            "answer": "<p><strong>Jawaban:</strong></p><p> A bebas  </p><p><strong>Penjelasan:</strong></p><p>semoga membantu </p><p></p><p>maaf kalo salah jawaban nya </p>",
            "attachments": []
        }
    ],
    "related_questions": [
        {
            "slug": "teknik-dribbling-dalam-sepak-bola-dapat-dilakukan-dengan-berbagai-811",
            "question": "Teknik dribbling dalam sepak bola dapat dilakukan dengan berbagai bagian kaki.    Tuliskan bagian-bagian kaki tersebur!\r\nuteril\u200b",
            "attachments": [],
            "answers": [
                {
                    "answer": "Teknik dribbling dalam sepak bola dapat dilakukan dengan berbagai bagian kaki.<br>Tuliskan bagian-bagian kaki tersebur!<br>uteril       JAWABAN:   Kaki kiri dan kanan",
                    "attachments": []
                }
            ]
        },
        {
            "slug": "i-will-follow-you-you-go-710",
            "question": "I will follow you .... You go.\u200b",
            "attachments": [],
            "answers": [
                {
                    "answer": "<p>Anywhere ( kemana pun )</p><p></p><p>( aku akan mengikuti mu <em>kemana</em><em> </em><em>pun </em>kau pergi )</p><p></p><p>semoga membantu.</p>",
                    "attachments": []
                },
                {
                    "answer": "<p><strong>Penjelasan:</strong></p><p>i will follow you <strong>w</strong><strong>h</strong><strong>e</strong><strong>r</strong><strong>e</strong><strong>v</strong><strong>e</strong><strong>r</strong><strong> </strong>you go</p>",
                    "attachments": []
                }
            ]
        },
        {
            "slug": "big-poin-kalau-1-jawaban-5-kalau-2-jawaban-10-1-renang-gaya-dad-135",
            "question": "Big poin    Kalau 1 jawaban 5, kalau 2 jawaban 10\r\n\r\n1. Renang gaya dada versi Canada dalam melakukan sapuan telapak tangan dengan air membentuk sudut \r\n\r\nA. 25-30 derajat\r\n\r\nB. 30-40 derajat \r\n\r\nC. 45-50 derajat \r\n\r\nD. 30-45 derajat \r\n\r\n2. Pengertian Tolakan menurut cabang lompat jauh adalah \r\n\r\nA. Perpindahan dekat ke jauh \r\n\r\nB. Perpindahan tubuh ke bak pasir\r\n\r\nC. Perpindahan dari gerakan horizontal ke vertikal secara cepat dan tepat pada papan tolakan\r\n\r\nD. Perpindahan dari gerakan sifat ke horizontal secara cepat dan tepat pada papan tolakan\u200b",
            "attachments": [],
            "answers": [
                {
                    "answer": "<p><strong>Jawaban:</strong></p><ol><li>D. 30 - 45 derajat</li><li>C. Perpindahan dari gerakan horizontal ke vertikal secara cepat dan tepat pada papan tolakan</li></ol><p><strong>Penjelasan:</strong></p><p>No 2. </p><ul><li>Teknik tolakan dalam olahraga lompat jauh adalah gerakan melompat meninggalkan tanah dengan menggunakan satu kaki terkuat. Tujuan dari teknik tolakan adalah agar badan terangkat dan melayang di udara.</li></ul>",
                    "attachments": []
                }
            ]
        },
        {
            "slug": "ukara-ijo-patin-krasak-ukara-ing-dhuwur-menawa-ditulis-nganggo-ak-696",
            "question": "Ukara ijo patin Krasak ukara ing dhuwur menawa ditulis nganggo aksara jawa yaitu\u200b",
            "attachments": [],
            "answers": [
                {
                    "answer": "<p><strong>Jawaban:</strong></p><p>..............................</p><p><strong>Penjelasan:</strong></p><p>.</p><p></p>",
                    "attachments": []
                }
            ]
        },
        {
            "slug": "sebutkan-2-model-latihan-dari-aspek-kebugaran-jasmani-dibawah-ini-956",
            "question": "Sebutkan 2 model latihan dari aspek kebugaran jasmani dibawah ini: a.kelincahan b.kecepatan\u200b",
            "attachments": [],
            "answers": [
                {
                    "answer": "<p><strong>Jawaban:</strong></p><p>kelincahan dalam berlari</p>",
                    "attachments": []
                }
            ]
        },
        {
            "slug": "urutkan-gerakan-smash-permainan-bola-voli-913",
            "question": "Urutkan gerakan smash permainan bola voli",
            "attachments": [],
            "answers": [
                {
                    "answer": "<p><strong>Jawaban:</strong></p><p>\u2022Mengambil langkah awalan sekitar 1 sampai 3 langkah.</p><p>\u2022Langkah yang diambil merupakan langkah kaki yang lebar.</p><p>\u2022Ketika mendekati net, ayunkan kedua lengan ke belakang.</p><p>\u2022Hentakkan kedua kaki bersusulan, lalu lompat.</p><p>Kemudian lengan yang akan memukul mulai \u2022diayunkan ke depan, dan punggung menegang ke belakang.</p><p></p><p></p><p>#maaf klo salah</p><p></p>",
                    "attachments": []
                }
            ]
        },
        {
            "slug": "gerakan-tolak-peluru-dimana-awalan-menyamping-sudut-lemparan-dina-386",
            "question": "Gerakan tolak peluru dimana awalan menyamping sudut lemparan dinamakan\u200b",
            "attachments": [],
            "answers": [
                {
                    "answer": "<p><strong>Jawaban:</strong></p><p>gaya ortodok</p><p><strong>Penjelasan:</strong></p><p>maaf kl salah</p>",
                    "attachments": []
                }
            ]
        },
        {
            "slug": "gerakan-bertumpu-ada-berapa-rangkaian-gerak-407",
            "question": "Gerakan bertumpu ada berapa rangkaian gerak",
            "attachments": [],
            "answers": [
                {
                    "answer": "<p><strong>Jawaban: Gerakan bertumpu dengan tangan dan gerakan bertumpu dengan kaki.\n</strong></p><p><strong>\n</strong></p><p><strong> </strong></p><p></p><p><strong>Penjelasan: Maap kalo salah </strong></p><p><strong></strong></p><p></p>",
                    "attachments": []
                }
            ]
        },
        {
            "slug": "tolong-dibantu-ya-209",
            "question": "Tolong dibantu ya....\u200b",
            "attachments": [
                "question-attachments/tolong-dibantu-ya-209-1.jpg"
            ],
            "answers": [
                {
                    "answer": "<p><strong>Jawaban:</strong></p><p>14.C</p><p>15.D</p><p>16.B</p><p>17.C</p><p>18.D</p><p>19.A</p><p>20.D</p><p><strong>Penjelasan:</strong></p><p><em>S</em><em>E</em><em>M</em><em>O</em><em>G</em><em>A</em><em> </em><em>M</em><em>E</em><em>M</em><em>B</em><em>A</em><em>N</em><em>T</em><em>U</em></p>",
                    "attachments": []
                }
            ]
        },
        {
            "slug": "agar-karya-kerajinan-lebih-indah-dan-menarik-perlu-untuk-742",
            "question": "Agar karya kerajinan lebih indah dan menarik perlu untuk...\u200b",
            "attachments": [],
            "answers": [
                {
                    "answer": "<p><strong>Jawaban:</strong></p><p></p><h3>Kerajinan Lebih indah Dan Menarik:</h3><p>-Menghiasi Kerajinan</p><p>-Warna Yang Serasi</p><p>-Mengasih Manik Manik </p><p></p><h2>Semoga Bermanfaat Ya</h2>",
                    "attachments": []
                }
            ]
        }
    ]
}