{
    "question": "Tentukan luas permukaan sebuah kubus yang memiliki panjang rusuk 5,3 cm    di bantu yah kak ntar aku follow\u200b",
    "attachments": [],
    "answers": [
        {
            "answer": "<p><strong>Jawaban:</strong></p><p>jawabannya adalah 28,09</p>",
            "attachments": []
        },
        {
            "answer": "<p>L = 168,54 cm\u00b2</p><p></p><p><strong>Penjelasan dengan langkah-langkah:</strong></p><p>r = 5,3 cm</p><p>L = 6r\u00b2</p><p>   = 6 x 5,3 cm x 5,3 cm</p><p>   = 168,54 cm\u00b2</p>",
            "attachments": []
        }
    ],
    "related_questions": [
        {
            "slug": "mohon-di-bantu-yaa-ka-613",
            "question": "Mohon di bantu yaa ka:)\u200b",
            "attachments": [
                "question-attachments/mohon-di-bantu-yaa-ka-613-1.jpg"
            ],
            "answers": [
                {
                    "answer": "<p><strong>Jawaban:</strong></p><p>modus = 6</p><p>median= 6+6\u00f72 =6  </p><p></p><p></p><p><strong>Penjelasan dengan langkah-langkah:</strong></p><p>semoga membantu</p>",
                    "attachments": []
                }
            ]
        },
        {
            "slug": "kakek-mempunyai-persediaan-makanan-untuk-6-ekor-kambing-selama-12-307",
            "question": "Kakek mempunyai persediaan makanan untuk 6 ekor kambing selama 12 hari.    Jika kemudian kakek membeli kambing sebanyak 2 ekor lagi, maka persediaan\r\n\r\nitu akan habis dalam .... hari\r\n\r\nA.10\r\n\r\nB.9\r\n\r\nC.8\r\n\r\nD.7\u200b",
            "attachments": [],
            "answers": [
                {
                    "answer": "<p><strong>Jawaban:</strong></p><p>B.9 hari</p><p><strong>Penjelasan dengan langkah-langkah:</strong></p><p>6 \u00d7 12 = 72</p><p>itung saja kakek memiliki 72 persediaan makanan</p><p>72 : (6+2) = 9</p><p></p><h3>jadi persediaan tersebut akan habis dalam waktu B.9 hari</h3>",
                    "attachments": []
                }
            ]
        },
        {
            "slug": "tolong-siapa-yang-bisa-jawab-please-soal-nya-besok-mau-di-kumpulk-943",
            "question": "Tolong Siapa Yang Bisa Jawab Please Soal Nya Besok Mau Di Kumpulkan!!!\u200b",
            "attachments": [
                "question-attachments/tolong-siapa-yang-bisa-jawab-please-soal-nya-besok-mau-di-kumpulk-943-1.jpg"
            ],
            "answers": [
                {
                    "answer": "<p><strong>Jawaban:</strong></p><p>5,6 cm</p><p><strong>Penjelasan dengan langkah-langkah:</strong></p><p>          PT/7 = PT + 2,4 / 10</p><p>      10 x PT = 7 x ( PT + 2,4)</p><p>          10PT = 7PT + 16,8</p><p>10PT - 7PT = 16,8</p><p>           3PT = 16,8</p><p>             PT = 16,8/3</p><p>             PT = 5,6</p>",
                    "attachments": []
                }
            ]
        },
        {
            "slug": "quis-hasil-dari-8-6-24-3-10-adalah-a-30-b-343",
            "question": "Quis    Hasil dari (-8) \u00d7 (-6) + 24 : (-3) - (-10) adalah\r\n\r\nA. 30\r\nB. 34\r\nC. 46\r\nD. 49\r\nE. 50\r\nF. 56\r\nG. 66\r\nH. Jawaban Lain (.....)?\u200b",
            "attachments": [],
            "answers": [
                {
                    "answer": "<p></p><h2>E. 50</h2><p></p><p><strong>Penjelasan dengan langkah-langkah:</strong></p><p>= (-8) \u00d7 (-6) + 24 : (-3) - (-10)</p><p>= 48 + (-8) + 10</p><p>= 48 - 8 + 10</p><p>= 40 + 10</p><p>= 50</p><p></p><h3>Pelajari lebih lanjut : </h3><ul><li>Hasil dari {-8 x [-9 x (-17 + 10)]} : brainly.co.id/tugas/30238449</li><li>Cara penghitungan -30 - (45 -(-27) : brainly.co.id/tugas/30237476</li><li>Hasil dari 17 \u00d7 (-4) + 325 \u00d7 (-3) : brainly.co.id/tugas/30239215</li><li>Hasil dari -650 : 50 + 13 - (-26) : brainly.co.id/tugas/30238934</li></ul><p></p><h3>Detail Jawaban</h3><p>Kelas\u00a0 : 5 (V) SD</p><p>Mapel : Matematika</p><p>Materi : Bab 1 -\u00a0 Operasi Hitung Bilangan \ufeffBulat </p><p>Kode kategorisasi : 5.2.1</p><p>Kata Kunci : (-8) \u00d7 (-6) + 24 : (-3) - (-10)</p>",
                    "attachments": []
                },
                {
                    "answer": "<h2>\u2740Penyelesaian-\u2728</h2><p>[tex]\\:[/tex]</p><p>[tex] \\sf{-8\u00d7(-6)+24\u00f7(-3)-(-10)} \\\\\u21d2\\sf{48+24\u00f7(-3)-(-10)} \\\\\u21d2\\sf{48+(-8)-(-10)} \\\\\u21d2\\sf{40-(-10)} \\\\\u21d2\\sf{50} [/tex]</p><p><strong>J\u03b1w\u03b1\u03b2\u03b1nny\u03b1 </strong>=&gt; [tex]{\\boxed{\\sf{\\pink{Opsi \\: E}}}} [/tex]</p>",
                    "attachments": []
                }
            ]
        },
        {
            "slug": "ibu-memotong-bika-ambon-menjadi-8-bagian-sama-besarayah-memakan-232",
            "question": "Ibu memotong bika ambon menjadi 8 bagian sama besar.ayah memakan 2 potong bika ambon .besar bagian yang di makan ayah adalah",
            "attachments": [],
            "answers": [
                {
                    "answer": "<p>1 bika ambon di potong menjadi 8 bagian maka masing masing menjadi 1/8</p><p>karna ayah memakan 2 potong maka tinggal kita kalikan 2\u00d71/8</p><p>2/8 lalu sederhanakan menjadi 1/4 bagian dari bika ambon</p><p></p><p>jadikan jawaban yang terbaik jika jawaban ini benar :) terima kasih</p>",
                    "attachments": []
                }
            ]
        },
        {
            "slug": "sebuah-belah-ketupat-diketahui-panjang-sisinya-17-cm-dan-salah-sa-327",
            "question": "sebuah belah ketupat diketahui panjang sisinya 17 cm dan salah satu diagonalnya 16 cm Tentukan luas belah ketupat tersebut\u200b",
            "attachments": [],
            "answers": [
                {
                    "answer": "<h2> <strong><em><u>30cm</u></em></strong></h2><p></p><p> </p><p></p><p>x\u00b2 = 17\u00b2 - 8\u00b2</p><p>x = \u221a289-64</p><p>x = \u221a225</p><p>x = 15 cm</p><p></p><p>panjang salah satu diagonal = 15 x 2 = 30 cm</p><p></p><p>Jadikan Jawaban terbaik jika anda merasa terbantu \u2728</p>",
                    "attachments": []
                }
            ]
        },
        {
            "slug": "di-antara-perbandingan-di-bawah-ini-yang-senilai-dengan-35-adala-225",
            "question": "Di antara perbandingan di bawah ini yang senilai dengan 3:5 adalah",
            "attachments": [],
            "answers": [
                {
                    "answer": "<p><strong>Jawaban:</strong></p><p>3:5 = 6:10 = 9:15 = 12:20 = 15: 25</p>",
                    "attachments": []
                }
            ]
        },
        {
            "slug": "shely-quis-101223-7-no-co-265",
            "question": "\u2618\u25cf\u25ac\u25ac\u0e51\u2741shely\u2741\u0e51\u25ac\u25ac\u25cf\u2618    Quis \r\n\r\n10+12+23-7 =\r\n\r\nNO COPAS\r\nNO GOOGLE\r\nSIAPA CEPAT DIA DAPAT\u200b",
            "attachments": [],
            "answers": [
                {
                    "answer": "<p><strong>Jawaban:</strong></p><p>38</p><p><strong>Penjelasan dengan langkah-langkah:</strong></p><p>10+12+23-7</p><p>22+23-7</p><p>45-7</p><p>38</p><p></p><h3>Semoga membantu...</h3><h3>Jadikan jawaban terbaik yaa...</h3>",
                    "attachments": []
                },
                {
                    "answer": "<h3>Pendahuluan </h3><p>Soal tersebut Termasuk Materi <strong>penjumlahan </strong><strong>,</strong><strong>Dalam</strong><strong> </strong><strong>Matematika </strong><strong>Terdapat </strong><strong>Bermacam</strong><strong> </strong><strong>-</strong><strong> </strong><strong>Macam</strong><strong> </strong><strong>Cara</strong><strong> </strong><strong>untuk</strong><strong> </strong><strong>menghitung</strong><strong> </strong><strong>suatu </strong><strong>bilangan </strong><strong>mulai</strong><strong> </strong><strong>dari</strong><strong> </strong><strong>Penjumlahan </strong><strong>Maupun</strong><strong> </strong><strong>Pengurangan</strong><strong>.</strong></p><p></p><p>A.Apa Itu <strong>Penjumlahan</strong><strong> </strong><strong>?</strong></p><p><strong>Penjumlahan</strong><strong> </strong><strong>atau</strong><strong> </strong><strong>dapat</strong><strong> </strong><strong>kita</strong><strong> </strong><strong>sebut</strong><strong> </strong><strong>sebagai</strong><strong> </strong><strong>penambahan</strong><strong> </strong><strong>merupakan </strong><strong>suatu</strong><strong> </strong><strong>Cara</strong><strong> </strong><strong>dalam</strong><strong> </strong><strong>matematika</strong><strong> </strong>yaitu menggabungkan Sekelompok bilangan dengan bilangan lain nya yang bisa Menjadi Nominal ,angka,jumlah atau pun Bilangan yang Bernilai Tinggi .</p><p></p><p>B.Apa itu <strong>pengurangan</strong><strong> </strong><strong>?</strong></p><p><strong>Pengurangan</strong><strong> </strong>merupakan cara dalam Matematika yaitu Mengurangi ,nominal,jumlah suatu angka .</p><p></p><h3>Langkah Penyelesaian :</h3><p></p><p>( <strong>Penjumlahan</strong><strong> </strong>)</p><p></p><p>= 10 + 12 + 23 - 7 </p><p>= 10 + 12 </p><p>= 22 + 23 </p><p>= 45 - 7</p><p>= 38 </p><p>____________________________</p><h3>Pelajari Lebih lanjut :</h3><p>\u2022 pengertian Bilanga Ganjil </p><p>=&gt; https://brainly.co.id/tugas/15566985</p><p>____________________________</p><h3><strong>Detail</strong><strong> </strong><strong>jawaban</strong><strong> </strong><strong>:</strong></h3><p><strong>Mapel</strong><strong> </strong>: Matematika</p><p><strong>kelas</strong><strong> </strong>: - SD</p><p><strong>kategori</strong><strong> </strong><strong>:</strong><strong> </strong>penjumlahan serta Pengurangan.</p><p><strong>kode</strong><strong> </strong><strong>soal</strong><strong> </strong>: 2</p><p><strong>kata</strong><strong> </strong><strong>kunci </strong>: Pengertian Penjumlahan , pengurangan .</p><p></p><p>[tex]\\red{\\boxed{\\tt \\:Answer\\: By {\\boxed{\\tt \\: me }}}}[/tex]</p>",
                    "attachments": [
                        "answer-attachments/shely-quis-101223-7-no-co-265-1.jpg"
                    ]
                }
            ]
        },
        {
            "slug": "volume-bak-mandi-24389-literpanjang-rusuj-bak-mandi-trb-adalah-796",
            "question": "Volume bak mandi 24.389 liter.panjang rusuj bak mandi trb adalah...dm",
            "attachments": [],
            "answers": [
                {
                    "answer": "<p><strong>Jawaban:</strong></p><p></p><p>Volume = S x S x S</p><p>Volume = 24.389 liter</p><p>24.389 = S\u00b3</p><p>S = \u2713\u00b3 24.389</p><p>S = 29 liter</p><p></p>",
                    "attachments": []
                }
            ]
        },
        {
            "slug": "besar-sudut-yg-dibentuk-oleh-jarum-jam-0820-adalah-282",
            "question": "Besar sudut yg dibentuk oleh jarum jam 08.20 adalah",
            "attachments": [],
            "answers": [
                {
                    "answer": "<p><strong>Jawaban:</strong></p><p>120\u00b0</p><p><strong>Penjelasan dengan langkah-langkah:</strong></p><p>setiap jarum jam bergerak lima menit, besar sudut yang terbentuk adalah 30\u00b0</p><p></p><p>jadi, besar sudut uang dibentuk adalah 120\u00b0</p><p></p>",
                    "attachments": []
                },
                {
                    "answer": "<p>Bayangkan kondisi saat jarum jam menunjukkan pukul 08.20 </p><p></p><p>jarum panjang terletak tepat di angka 4 </p><p>jarum pendek bergerak menjauhi searah jarum jam dari angka 8 sehingga sekarang terletak pada titik yang melebihi angka 8</p><p></p><p>Hitung besar sudut dari tepat angka 8 hingga ke titik jarum pendek berada</p><p>[tex]\\frac{20}{60}\\times 30\u00b0=10\u00b0[/tex]</p><p>Hitung total sudut, yaitu dari angka 4 hingga tepat angka 8 ditambah 10\u00b0</p><p>[tex]4\\times 30\u00b0 + 10\u00b0=130\u00b0[/tex]</p><p></p><p>Jadi, besar sudut terkecil yang dibentuk oleh jarum jam pukul 08.20 adalah 130\u00b0</p><p></p>",
                    "attachments": []
                }
            ]
        }
    ]
}