{
    "question": "Tolong jawab dentan benar \u200b",
    "attachments": [
        "question-attachments/tolong-jawab-dentan-benar-905-1.jpg"
    ],
    "answers": [
        {
            "answer": "<p>Urutan perpecahan dri yng terkecil</p><p>12/ 5; 3/4; 0,5 (A)</p>",
            "attachments": []
        }
    ],
    "related_questions": [
        {
            "slug": "untuk-membuat-6-kerangka-persegi-diperlukan-kawat-dengan-panjang-912",
            "question": "untuk membuat 6 kerangka persegi diperlukan kawat dengan panjang 18 m jika panjang kawat yang tersedia 42 m Berapa banyak kerangka persegi yang dapat dibuat\u200b",
            "attachments": [],
            "answers": [
                {
                    "answer": "<p>perbandingan seharga </p><p>6/18 = x/42</p><p>1/3 = x/42</p><p>3x = 42</p><p>x = 14 kerangka persegi</p>",
                    "attachments": []
                }
            ]
        },
        {
            "slug": "quizz-time-asli-quiz-bukan-tugas-387",
            "question": "Quizz Time!!!!\r\n\r\n\r\n\r\n*asli quiz bukan tugas\u200b",
            "attachments": [],
            "answers": [
                {
                    "answer": "<p><strong>Jawaban:</strong></p><p><strong>9</strong><strong>0</strong></p><p><strong>Penjelasan dengan langkah-langkah:</strong></p><p>langkah cara ada di gambar</p>",
                    "attachments": [
                        "answer-attachments/quizz-time-asli-quiz-bukan-tugas-387-1.jpg"
                    ]
                },
                {
                    "answer": "<p><strong>Jawaban:</strong></p><p>90</p><p><strong>Penjelasan dengan langkah-langkah:</strong></p><p>\u00b3\u221a729000 adalah 90</p><p>Caranya simpel aja</p><p>\u00b3\u221a729 kan 9</p><p>\u00b3\u221a1000 kan 10</p><p>729 \u00d7 1000 = 729000</p><h3><strong><u>9 \u00d7 10 = 90</u></strong></h3>",
                    "attachments": []
                }
            ]
        },
        {
            "slug": "cara-penyelesaian-untuk-mencari-nilai-x-jawabannya-please-934",
            "question": "Cara penyelesaian untuk mencari nilai x. Jawabannya please. \u200b",
            "attachments": [
                "question-attachments/cara-penyelesaian-untuk-mencari-nilai-x-jawabannya-please-934-1.jpg"
            ],
            "answers": [
                {
                    "answer": "<p><strong>Jawaban:</strong></p><p>ngga tau,jwb sendiri napa</p>",
                    "attachments": []
                }
            ]
        },
        {
            "slug": "tentukan-himpunan-penyelesaian-dari-kedua-persamaan-berikut-denga-339",
            "question": "Tentukan himpunan penyelesaian dari kedua persamaan berikut dengan metode eliminasi 2x + y = 4 dan 3x + 2y =7\u200b",
            "attachments": [],
            "answers": [
                {
                    "answer": "<p><strong><em>hp </em></strong><strong><em>=</em></strong><strong><em> </em></strong><strong><em>{</em></strong><strong><em>1</em></strong><strong><em>,</em></strong><strong><em>2</em></strong><strong><em>}</em></strong></p><p></p><p><strong>Penjelasan dengan langkah-langkah:</strong></p><p>cara penyelesaian terlampir pada gambar ya..</p><p></p><p><em>semoga</em><em> bermanfaat</em><em>:</em><em>)</em></p><p></p>",
                    "attachments": [
                        "answer-attachments/tentukan-himpunan-penyelesaian-dari-kedua-persamaan-berikut-denga-339-1.jpg"
                    ]
                }
            ]
        },
        {
            "slug": "luas-persegi-yang-panjang-diagonal-sisinya-8-cm-adalah-137",
            "question": "Luas persegi yang panjang diagonal sisinya 8 cm adalah..\u200b",
            "attachments": [],
            "answers": [
                {
                    "answer": "<p><strong>JAWABAN</strong><strong> </strong><strong>:</strong><strong> </strong><strong>S</strong><strong> </strong><strong>X</strong><strong> </strong><strong>S</strong><strong> </strong></p><p><strong> </strong><strong> </strong><strong> </strong><strong> </strong><strong> </strong><strong> </strong><strong> </strong><strong> </strong><strong> </strong><strong> </strong><strong> </strong><strong> </strong><strong> </strong><strong> </strong><strong> </strong><strong> </strong><strong> </strong><strong> </strong><strong> </strong><strong>:</strong><strong> </strong><strong>8</strong><strong> </strong><strong>X</strong><strong> </strong><strong>8</strong></p><p><strong> </strong><strong> </strong><strong> </strong><strong> </strong><strong> </strong><strong> </strong><strong> </strong><strong> </strong><strong> </strong><strong> </strong><strong> </strong><strong> </strong><strong> </strong><strong> </strong><strong> </strong><strong> </strong><strong> </strong><strong> </strong><strong> </strong><strong>:</strong><strong> </strong><strong>6</strong><strong>4</strong><strong> </strong><strong>CM</strong><strong>\u00b2</strong></p><p></p><p><strong>Penjelasan dengan langkah-langkah:</strong></p><p>rumus luas persegi = s x s</p>",
                    "attachments": []
                },
                {
                    "answer": "<p><strong>Jawaban:</strong></p><p><strong>64</strong><strong> </strong><strong>cm\u00b2</strong></p><p><strong>Penjelasan dengan langkah-langkah:</strong></p><p><strong>Luas</strong><strong> </strong><strong>Persegi</strong></p><p><strong>[tex] = s \\times s[/tex]</strong></p><p><strong>[tex] = 8 \\times 8[/tex]</strong></p><p><strong>[tex] = 64 \\:  {cm}^{2} [/tex]</strong></p><p><strong><em>Semoga</em></strong><strong><em> </em></strong><strong><em>Membantu</em></strong><strong><em> </em></strong><strong><em>:</em></strong><strong><em>)</em></strong><strong><em> </em></strong></p>",
                    "attachments": []
                }
            ]
        },
        {
            "slug": "besar-bayangan-yang-dibentuk-oleh-cermin-cekung-3-kali-bendanya-j-572",
            "question": "besar bayangan yang dibentuk oleh cermin cekung 3 kali bendanya jika jarak benda ke cermin 10 cm hitunglah jarak titik fokus cermin tersebut\u200b",
            "attachments": [],
            "answers": [
                {
                    "answer": "<p>f = 7,5 cm</p><p></p><p><strong>Penjelasan dengan langkah-langkah:</strong></p><p>s = 10 cm</p><p>s&#039; = 3 x 10 cm = 30 cm</p><p></p><p>1/f = 1/s + 1/s&#039;</p><p>     = 1/10 + 1/30</p><p>     = 3/30 + 1/30</p><p>     = 4/30</p><p>f = 30/4 = 7,5 cm</p>",
                    "attachments": []
                }
            ]
        },
        {
            "slug": "budi-akan-membuat-bangun-ruang-kubus-dengan-volume-1728cm3bera-838",
            "question": "Budi akan membuat bangun ruang kubus dengan volume 1.728cm.\u00b3berapa cm\u00b2 kertas yang diperlukan budi untuk membuat jaring jaring kubus tersebut?",
            "attachments": [],
            "answers": [
                {
                    "answer": "<p>864 cm\u00b2</p><p></p><p><strong>Penjelasan dengan langkah-langkah:</strong></p><p>V = 1.728 cm</p><p>r = \u00b3\u221a1.728</p><p>  = \u00b3\u221a(12 x 12 x 12)</p><p>  = 12 cm</p><p></p><p>kertas yang diperlukan berarti Luas</p><p>L = 6 r\u00b2</p><p>   = 6 x 12 x 12</p><p>   = 864 cm\u00b2</p>",
                    "attachments": []
                }
            ]
        },
        {
            "slug": "jika-ketiga-kepingan-uang-logam-di-lemparkan-sekaligus-jumlah-kej-376",
            "question": "jika ketiga kepingan uang logam di lemparkan sekaligus jumlah kejadian yang mungkin terjadi seliruh nya sebanyak\u200b",
            "attachments": [],
            "answers": [
                {
                    "answer": "<p><strong>Jawaban:</strong></p><p>(AAA), (AAG), (AGA), (AGG), (GAA), (GAG), (GGA), (GGG) = 8 kali</p><p><strong>Penjelasan dengan langkah-langkah:</strong></p><p>Semoga membantu.</p>",
                    "attachments": []
                }
            ]
        },
        {
            "slug": "17-sisi-persegi-128-cm-keliling-cm-a512-b256-409",
            "question": "17. Sisi persegi 128 cm. Keliling \u2026\u2026\u2026\u2026 cm. *    a.512\r\n\r\nb.256\r\n\r\nc.521\r\n\r\nd.516\r\n\r\nYang lain:\r\n\r\n18. Mean dari deretan angka 82, 88, 86, 90, 94, 84, 86, 86, 96 ialah \u2026\u2026\u2026\u2026 *\r\n\r\na.78\r\n\r\nb.88\r\n\r\nc.8,8\r\n\r\nd.98\r\n\r\n19. Median dari deretan angka 81, 72, 77, 92, 84, 72, 82, 96, 74, 94 ialah \u2026\u2026\u2026\u2026 *\r\n\r\na.81\r\n\r\nb.80,5\r\n\r\nc.82\r\n\r\nd.81,5\r\n\r\n20. Mean dari deretan angka 178, 154, 146, 152, 172, 148, 128 ialah \u2026\u2026\u2026\u2026 *\r\n\r\na.153,5\r\n\r\nb.144\r\n\r\nc.154\r\n\r\nd.164\r\n\r\n21. 7 km + 80 dam = \u2026\u2026\u2026\u2026 m. *\r\n\r\na.7.080\r\n\r\nb.7.800\r\n\r\nc.780\r\n\r\nd.1.500\r\n\r\n22. 9 km - 15hm = \u2026\u2026\u2026\u2026 dm. *\r\n\r\na.9.150\r\n\r\nb.8.850\r\n\r\nc.7.500\r\n\r\nd.75.000\r\n\r\n23. 12.000 m + 50 km = \u2026\u2026\u2026\u2026 hm. *\r\n\r\na.12.050\r\n\r\nb.12.500\r\n\r\nc.620\r\n\r\nd.1.250\r\n\r\n24. Median dari deretan angka 152, 148, 136, 150, 124, 156, 140, 142 ialah \u2026\u2026\u2026\u2026. *\r\na.145\r\n\r\nb.142\r\n\r\nc.148\r\n\r\nd.144\u200b",
            "attachments": [],
            "answers": [
                {
                    "answer": "<p><strong>Jawaban:</strong></p><p>17.  128 kali 128= a. 512 </p><p>yang lain gak tau</p><p> </p>",
                    "attachments": []
                }
            ]
        },
        {
            "slug": "alas-sebuah-limas-berbentuk-belah-ketupat-dengan-panjang-sisi-13-761",
            "question": "Alas sebuah limas berbentuk belah ketupat dengan panjang sisi 13 cm, panjang salah satu diagonalnya 24 cm, dan tinggi limas 15 cm, maka volume limas adalah....cm 3    a. 600\r\nb. 900\r\nc. 1.200\r\nd. 1.800\u200b",
            "attachments": [],
            "answers": [
                {
                    "answer": "<p><strong>Penjelasan dengan langkah-langkah:</strong></p><p>Volume limas belah ketupat = 600</p>",
                    "attachments": [
                        "answer-attachments/alas-sebuah-limas-berbentuk-belah-ketupat-dengan-panjang-sisi-13-761-1.jpg"
                    ]
                }
            ]
        }
    ]
}