{
    "question": "You can find places in the word on the globe. The globe is like\u200b",
    "attachments": [],
    "answers": [
        {
            "answer": "<p>Globe is like miniature of the world</p>",
            "attachments": []
        }
    ],
    "related_questions": [
        {
            "slug": "susun-kata2-berikut-ini-teacher-some-brings-book-303",
            "question": "Susun kata\u00b2 berikut ini\r\n teacher some brings book\u200b",
            "attachments": [],
            "answers": [
                {
                    "answer": "<p>English : Teacher Bring Some Book</p><p>Indonesia : Guru memberikan beberapa buku</p><p></p>",
                    "attachments": []
                },
                {
                    "answer": "<p><strong>Jawaban:</strong></p><p>teacher brings some book</p><p><strong>translate:</strong></p><p>guru membawa beberapa buku</p><p></p>",
                    "attachments": []
                }
            ]
        },
        {
            "slug": "the-students-usually-the-books-in-the-libary-at-the-break-809",
            "question": "The students usually ...... the books in the libary at the break time.\u200b",
            "attachments": [],
            "answers": [
                {
                    "answer": "<p><strong>Jawaban:</strong></p><p>the students usually read the books in the libary at the break time</p><p><strong>Penjelasan:</strong></p><p>hy namaku alex</p><p>ak agama katolik</p><p>salken ^_^</p><p></p>",
                    "attachments": [
                        "answer-attachments/the-students-usually-the-books-in-the-libary-at-the-break-809-1.jpg"
                    ]
                }
            ]
        },
        {
            "slug": "tolong-bantu-kak-plisss-besok-mau-dikumpul-868",
            "question": "Tolong bantu kak plisss besok mau dikumpul...\u200b",
            "attachments": [
                "question-attachments/tolong-bantu-kak-plisss-besok-mau-dikumpul-868-1.jpg"
            ],
            "answers": [
                {
                    "answer": "<p><strong>Jawaban:</strong></p><p>13.A</p><p><strong>Penjelasan:</strong></p><p>maaf kalau salah Semoga membantu dan bermanfaat</p>",
                    "attachments": []
                },
                {
                    "answer": "<p><strong>Jawaban:</strong></p><p>13 a</p><p>14 c</p><p>15 b</p><p>16 d</p><p>17 d</p><p><strong>Penjelasan:</strong></p><p>dah segitu gw capek muterin kepala</p><p></p>",
                    "attachments": []
                }
            ]
        },
        {
            "slug": "nilai-50-60-70-80-90-frekuensi-15-25-40-35-10-banyak-siswa-yang-m-824",
            "question": "Nilai    50 60 70 80 90\r\nFrekuensi 15 25 40 35 10\r\n Banyak siswa yang memperoleh nilai lebih dari 60 adalah.......\r\nb. 87 orang\r\na. 85 Orang\r\nc. 88 orang\r\nd. 90 orang\u200b",
            "attachments": [],
            "answers": [
                {
                    "answer": "<p><strong>Jawaban:</strong></p><p>70= 40 orang </p><p>80 = 35 orang </p><p>90 = 10 orang </p><p>total= 40+35+10</p><p>= 85 orang </p>",
                    "attachments": []
                }
            ]
        },
        {
            "slug": "tolong-50-poin-big-poin-plis-164",
            "question": "Tolong 50 poin\r\nbig poin plis\u200b",
            "attachments": [
                "question-attachments/tolong-50-poin-big-poin-plis-164-1.jpg"
            ],
            "answers": [
                {
                    "answer": "<p><strong>Jawaban:</strong></p><p>syaribna</p><p><strong>Penjelasan:</strong></p><p>maaf kalau salah, tapi setau saya itu</p>",
                    "attachments": []
                },
                {
                    "answer": "<p><strong>Jawaban:</strong></p><p>syaribna</p><p><strong>Penjelasan:</strong></p><p>maaf kalau salah</p><p></p>",
                    "attachments": []
                }
            ]
        },
        {
            "slug": "6-siti-i-have-a-toothache-lina-you-should-go-to-the-a-961",
            "question": "6. Siti : I have a toothache    Lina : You should go to the ....\r\na. doctor b. dentist c. lawyer\r\nd. hospital\u200b",
            "attachments": [],
            "answers": [
                {
                    "answer": "<p><strong>Jawaban:</strong></p><p>b. dentist</p><p><strong>Penjelasan:</strong></p><p>Karena Siti mengalami sakit gigi, maka Siti harus pergi ke dokter gigi (dentist).</p><p></p><p>Doctor = dokter</p><p>Dentist = dokter gigi</p><p>Lawyer = pengacara</p><p>Hospital = rumah sakit</p><p></p><p>Semoga membantu :)</p>",
                    "attachments": []
                },
                {
                    "answer": "<p><strong>Jawaban:</strong></p><p><strong>B. </strong><strong>dentist</strong></p><p><strong>Penjelasan:</strong></p><p><em>semoga </em><em>membantu </em></p>",
                    "attachments": []
                }
            ]
        },
        {
            "slug": "i-like-cocolatte-cocolatte-328",
            "question": "I like cocolatte cocolatte\u200b",
            "attachments": [],
            "answers": [
                {
                    "answer": "<p><strong>Jawaban:</strong></p><p>i like chocolate </p><p>i like chocolate</p>",
                    "attachments": []
                }
            ]
        },
        {
            "slug": "ii-read-the-text-and-answer-it-1-david-always-sing-a-song-ever-200",
            "question": "II.    Read the text and answer it!\r\n1. David always sing a song every single day. His hobby i\r\n2.\r\nDinda : \"What is this?\"\r\nMaya : \u201c What is this my water gun.\"\r\nwears - My - scarf - mother - market - at. Arrange\r\nmears my mother market scara\r\nThe month after June is\u200b",
            "attachments": [],
            "answers": [
                {
                    "answer": "<p><strong>Jawaban:</strong></p><p>July</p><p><strong>Penjelasan:</strong></p><p>semoga jawaban nya benar</p><p>kalo salah maaf ya</p>",
                    "attachments": []
                }
            ]
        },
        {
            "slug": "bantuin-jawab-hyung-tolong-jangan-asal-jawab-723",
            "question": "Bantuin jawab hyung(^.^)\r\n\r\ntolong jangan asal jawab!!!!!!!!!!!!!!\u200b",
            "attachments": [
                "question-attachments/bantuin-jawab-hyung-tolong-jangan-asal-jawab-723-1.jpg"
            ],
            "answers": [
                {
                    "answer": "<p><strong>Jawaban:</strong></p><p>1. A. Taller</p><p>2. B. 15.000,00</p><p>3. D. Small</p><p>4. A. Hunting</p><p>5. A. Post office</p><p>6. B. Bug</p><p>7. D. Asia</p><p><strong>Penjelasan:</strong></p><p>Semoga bermanfaat ^^</p><p>-Lily \u2728</p>",
                    "attachments": []
                }
            ]
        },
        {
            "slug": "tolong-di-jawab-dengan-benar-ya-kk-658",
            "question": "Tolong di jawab dengan benar ya kk.....\u200b",
            "attachments": [
                "question-attachments/tolong-di-jawab-dengan-benar-ya-kk-658-1.jpg"
            ],
            "answers": [
                {
                    "answer": "<p><strong>Jawaban:</strong></p><p>8.a</p><p>9.a</p><p>10.b</p><p>11.c</p><p>12.d</p><p>13.c</p><p>14.d</p><p><strong>Penjelasan:</strong></p><p>jadikan jawaban yang terbaik</p><p></p><p>jangan lupa follow </p><p></p><p>maaf kalau salah</p><p></p>",
                    "attachments": []
                },
                {
                    "answer": "<p><strong>Jawaban:</strong></p><p>8. b. reads</p><p>9. a. gets up</p><p>10. b. sweep</p><p>11. c. doctor</p><p>12. d. teacher</p><p>13. c. pilot</p><p>14. farmer</p>",
                    "attachments": []
                }
            ]
        }
    ]
}